sync_ram.v
module sync_ram #(
    parameter DATA_WIDTH = 8,
    parameter ADDR_WIDTH = 4
)(
    input clk,
    input en,                 // Enable
    input we,                 // Write Enable
    input [ADDR_WIDTH-1:0] addr,
    input [DATA_WIDTH-1:0] din,
    output reg [DATA_WIDTH-1:0] dout
);

    // Declare RAM memory
    reg [DATA_WIDTH-1:0] mem [0:(1<<ADDR_WIDTH)-1];

    always @(posedge clk) begin
        if (en) begin
            if (we)
                mem[addr] <= din;     // Write operation
            else
                dout <= mem[addr];    // Read operation
        end
    end

endmodule

sync_ram_tb.v
`timescale 1ns/1ps

module sync_ram_tb;

    // Signal declarations
    reg clk;
    reg en;
    reg we;
    reg [3:0] addr;
    reg [7:0] din;
    wire [7:0] dout;

    // Instantiate the DUT (Device Under Test)
    sync_ram uut (
        .clk(clk),
        .en(en),
        .we(we),
        .addr(addr),
        .din(din),
        .dout(dout)
    );

    // Clock generator: toggle every 5ns => 10ns period
    always #5 clk = ~clk;

    // VCD Dump for GTKWave
    initial begin
        $dumpfile("sync_ram_wave.vcd");
        $dumpvars(0, sync_ram_tb);
    end

    // Test sequence
    initial begin
        $display("Time\tclk\ten\twe\taddr\tdin\tdout");
        $monitor("%0t\t%b\t%b\t%b\t%h\t%h\t%h", $time, clk, en, we, addr, din, dout);

        // Initialization
        clk = 0; en = 0; we = 0; addr = 0; din = 0;

        #10 en = 1;

        // Write operations
        we = 1;
        addr = 4'h1; din = 8'hA5; #10;
        addr = 4'h2; din = 8'h3C; #10;
        addr = 4'h3; din = 8'h7F; #10;

        // Read operations
        we = 0;
        addr = 4'h1; #10;
        addr = 4'h2; #10;
        addr = 4'h3; #10;

        #20 $finish;
    end

endmodule

sync_ram_wave.vcd
$date
	Wed Jul 09 11:50:43 2025
$end
$version
	Icarus Verilog
$end
$timescale
	1ps
$end
$scope module sync_ram_tb $end
$var wire 8 ! dout [7:0] $end
$var reg 4 " addr [3:0] $end
$var reg 1 # clk $end
$var reg 8 $ din [7:0] $end
$var reg 1 % en $end
$var reg 1 & we $end
$scope module uut $end
$var wire 4 ' addr [3:0] $end
$var wire 1 # clk $end
$var wire 8 ( din [7:0] $end
$var wire 1 % en $end
$var wire 1 & we $end
$var reg 8 ) dout [7:0] $end
$upscope $end
$upscope $end
$enddefinitions $end
#0
$dumpvars
bx )
b0 (
b0 '
0&
0%
b0 $
0#
b0 "
bx !
$end
#5000
1#
#10000
0#
b10100101 $
b10100101 (
b1 "
b1 '
1&
1%
#15000
1#
#20000
0#
b111100 $
b111100 (
b10 "
b10 '
#25000
1#
#30000
0#
b1111111 $
b1111111 (
b11 "
b11 '
#35000
1#
#40000
0#
b1 "
b1 '
0&
#45000
b10100101 !
b10100101 )
1#
#50000
0#
b10 "
b10 '
#55000
b111100 !
b111100 )
1#
#60000
0#
b11 "
b11 '
#65000
b1111111 !
b1111111 )
1#
